{
  "variants": {
    "facing=east,summoning=false": {
      "model": "projectj:block/little_man_statue_block",
      "y": 90
    },
    "facing=east,summoning=true": {
      "model": "projectj:block/little_man_statue_block_summoning",
      "y": 90
    },
    "facing=north,summoning=false": {
      "model": "projectj:block/little_man_statue_block"
    },
    "facing=north,summoning=true": {
      "model": "projectj:block/little_man_statue_block_summoning"
    },
    "facing=south,summoning=false": {
      "model": "projectj:block/little_man_statue_block",
      "y": 180
    },
    "facing=south,summoning=true": {
      "model": "projectj:block/little_man_statue_block_summoning",
      "y": 180
    },
    "facing=west,summoning=false": {
      "model": "projectj:block/little_man_statue_block",
      "y": 270
    },
    "facing=west,summoning=true": {
      "model": "projectj:block/little_man_statue_block_summoning",
      "y": 270
    }
  }
}